Metadata-Version: 1.0
Name: testmodule1
Version: 0.1.0
Summary: A example Python package
Home-page: UNKNOWN
Author: Vladislav Gusev
Author-email: vladislav.sg@yandex.ru
License: UNKNOWN
Platform: UNKNOWN
